rtf_tokenize.cp313-win_amd64.pyd
rtf_tokenize-1.0.1.dist-info/licenses/LICENSE.txt
rtf_tokenize-1.0.1.dist-info/METADATA
rtf_tokenize-1.0.1.dist-info/WHEEL
rtf_tokenize-1.0.1.dist-info/top_level.txt
rtf_tokenize-1.0.1.dist-info/zip-safe
rtf_tokenize-1.0.1.dist-info/RECORD
